{
  "name": "Making a Drill",
  "icon": "gempire:drill_block",
  "advancement": "gempire:root",
  "category": "gempire:gem_creation_category",
  "pages": [
    {
      "type": "patchouli:spotlight",
      "link_recipe ": true,
      "item": "gempire:pebble_gem",
      "text": "In order to make a Drill, you will need a pebble. Please shift click the gem icon."
    },
    {
      "type": "patchouli:multiblock",
      "name": "Drill",
      "text": "In order to have your Pebble construct a Drill, you will need to build this multiblock, then interact with her with a pickaxe in your hand.",
      "multiblock": {
        "pattern": [
          [
            " I ",
            "I0I",
            " I "
          ]
        ],
        "mapping": {
          "I": "minecraft:iron_bars",
          "0": "minecraft:hopper"
        },
        "symmetrical": true
      }
    }
  ]
}