{
  "name": "Power Crystal Mk-II",
  "icon": "gempire:power_crystal_block_tier_2",
  "advancement": "gempire:injection/obtain_power_crystal",
  "category": "gempire:gem_creation_category",
  "pages": [
    {
      "type": "patchouli:spotlight",
      "item": "gempire:peridot_gem",
      "text": "In order to make an Advanced Power Crystal, you will need a Peridot.$(br2)To have your Peridot construct an Advanced Power Crystal, you will need to build this multiblock, set her movement mode to stay then right click on her with a pickaxe."
    },
    {
      "type": "patchouli:multiblock",
      "name": "Advanced Power Crystal",
      "multiblock": {
        "pattern": [
          [
            "_I_",
            "I0I",
            "_I_"
          ]
        ],
        "mapping": {
          "I": "gempire:prismatic_block",
          "0": "minecraft:redstone_block"
        },
        "symmetrical": true
      }
    }
  ]
}