{
  "display": {
    "icon": {
      "item": "gempire:topaz_gem_4"
    },
    "title": {
      "translate": "advancements.gempire.topaz.title"
    },
    "description": {
      "translate": "advancements.gempire.topaz.description"
    },
    "frame": "task",
    "hidden": true
  },
  "parent": "gempire:create_injector",
  "criteria": {
    "requirement": {
      "trigger": "minecraft:inventory_changed",
      "conditions": {
        "items": [
          {
            "tag": "gempire:topaz"
          }
        ]
      }
    }
  }
}
